mars_test
