Metadata-Version: 1.1
Name: mars-test1
Version: 0.0.5
Summary: mart_test
Home-page: UNKNOWN
Author: anonymous
Author-email: pratickyel@gmail.com
License: MIT
Keywords: donotdothat
Platform: UNKNOWN
Classifier: Development Status :: 5 - Production/Stable
Classifier: Intended Audience :: Education
Classifier: Operating System :: POSIX :: Linux
Classifier: License :: OSI Approved :: MIT License
Classifier: Programming Language :: Python :: 3.5
